[
  {
    "url": "https://links.sgx.com/1.0.0/corporate-announcements/FUK3PY2CS46OPXRV/22c04cce0754a3dad40d88739324d155c48c0ad5475cc78875af2c478f389d91",
    "symbol": "BN4",
    "purchase_date": "2025-12-12",
    "type": "On Market",
    "price_per_share": {
      "highest": 10.22,
      "lowest": 10.12
    },
    "total_value": 509737.01,
    "total_shares_purchased": 50000,
    "treasury_shares_after_purchase": 18297940,
    "mandate": {
      "mandate_total": 90741740,
      "cumulative_purchased": 12620000,
      "mandate_remaining": 78121740,
      "mandate_start": "2025-04-21",
      "mandate_end": "2026-04-21"
    }
  }
]